rpnet/__init__.py
rpnet/predict.py
rpnet/rpnet2skhash.py
rpnet_dev-0.0.12.dist-info/licenses/LICENSE.txt
rpnet_dev-0.0.12.dist-info/METADATA
rpnet_dev-0.0.12.dist-info/WHEEL
rpnet_dev-0.0.12.dist-info/top_level.txt
rpnet_dev-0.0.12.dist-info/RECORD
